workspace_generator/__init__.py
workspace_generator/cli.py
workspace_generator/generator.py
workspace_generator-1.0.1.dist-info/METADATA
workspace_generator-1.0.1.dist-info/WHEEL
workspace_generator-1.0.1.dist-info/entry_points.txt
workspace_generator-1.0.1.dist-info/top_level.txt
workspace_generator-1.0.1.dist-info/RECORD
